whecho/README.md
whecho/__init__.py
whecho/_config.py
whecho/_send_message.py
whecho/_utilities.py
whecho/whecho.py
whecho-0.0.5.dist-info/entry_points.txt
whecho-0.0.5.dist-info/LICENSE
whecho-0.0.5.dist-info/WHEEL
whecho-0.0.5.dist-info/METADATA
whecho-0.0.5.dist-info/RECORD
