Metadata-Version: 2.1
Name: whecho
Version: 0.0.5
Summary: Linux echo with webhooks! ⚓
Home-page: https://github.com/cvraut/whecho
License: MIT
Keywords: webhooks,notifications,echo,whecho,command-line,cli
Author: Chinmay Raut
Requires-Python: >=3.6
Classifier: Environment :: Console
Classifier: Intended Audience :: Developers
Classifier: Intended Audience :: System Administrators
Classifier: License :: OSI Approved :: MIT License
Classifier: Operating System :: Microsoft :: Windows :: Windows 10
Classifier: Operating System :: POSIX :: Linux
Classifier: Programming Language :: Python :: 3
Classifier: Programming Language :: Python :: 3.6
Classifier: Programming Language :: Python :: 3.7
Classifier: Topic :: Software Development :: Libraries :: Python Modules
Classifier: Topic :: System :: Logging
Classifier: Topic :: System :: Monitoring
Classifier: Topic :: Utilities
Requires-Dist: requests (>=2.25.1)
Requires-Dist: setuptools (>=40.6.3)
Requires-Dist: toml (>=0.6.0)
Project-URL: Repository, https://github.com/cvraut/whecho
